{
  "category": "feature",
  "description": "Generate scoped CSS Modules with proper naming conventions. Support composition and value imports. Generate TypeScript type definitions for CSS modules. Handle global styles appropriately.",
  "title": "CSS Modules Generator",
  "dependencies": [
    "css-framework-selection-interface"
  ],
  "priority": 55,
  "status": "verified",
  "branchName": "master",
  "id": "feature-1768844694892-2tlvic83d",
  "descriptionHistory": [
    {
      "description": "Generate scoped CSS Modules with proper naming conventions. Support composition and value imports. Generate TypeScript type definitions for CSS modules. Handle global styles appropriately.",
      "timestamp": "2026-01-19T17:44:54.892Z",
      "source": "initial"
    }
  ],
  "startedAt": "2026-01-20T05:32:03.161Z",
  "updatedAt": "2026-01-20T05:50:17.813Z"
}