{
  "category": "enhancement",
  "description": "Generate appropriate SEO metadata from design content. Create meta tags, Open Graph tags, and structured data. Support custom metadata templates. Validate against SEO best practices.",
  "title": "SEO Metadata Generator",
  "dependencies": [
    "semantic-element-detector"
  ],
  "priority": 102,
  "status": "backlog",
  "branchName": "master",
  "id": "feature-1768844694933-fxpwhnrjd",
  "descriptionHistory": [
    {
      "description": "Generate appropriate SEO metadata from design content. Create meta tags, Open Graph tags, and structured data. Support custom metadata templates. Validate against SEO best practices.",
      "timestamp": "2026-01-19T17:44:54.934Z",
      "source": "initial"
    }
  ]
}